{
  "db_name": "PostgreSQL",
  "query": "\n            INSERT INTO price_pool (timestamp, pool_id, token0, token1, token0_in_1_token1, token1_in_1_token0)\n            VALUES ($1, $2, $3, $4, $5, $6)\n            ",
  "describe": {
    "columns": [],
    "parameters": {
      "Left": [
        "Timestamptz",
        "Text",
        "Text",
        "Text",
        "Numeric",
        "Numeric"
      ]
    },
    "nullable": []
  },
  "hash": "a8d446473a1a6f1227009c4f57ae8787ead19cf9e4ceb1b575d3fe3aefa9cfff"
}
