{
  "db_name": "PostgreSQL",
  "query": "\n                INSERT INTO new_memecooking_meme_testnet (timestamp, transaction_id, receipt_id, block_height, meme_id, owner, end_timestamp_ms, name, symbol, decimals, total_supply, reference, reference_hash, deposit_token_id, soft_cap, hard_cap)\n                VALUES ($1, $2, $3, $4, $5, $6, $7, $8, $9, $10, $11, $12, $13, $14, $15, $16)\n                ",
  "describe": {
    "columns": [],
    "parameters": {
      "Left": [
        "Timestamptz",
        "Text",
        "Text",
        "Int8",
        "Int8",
        "Text",
        "Int8",
        "Text",
        "Text",
        "Int4",
        "Numeric",
        "Text",
        "Text",
        "Text",
        "Numeric",
        "Numeric"
      ]
    },
    "nullable": []
  },
  "hash": "96aa4dc46c81066fe5024c7c4c42767a8d89e6d151f16c6de294e6048cbca91f"
}
